turbocore/__init__.py
turbocore/__main__.py
turbocore/ai/__init__.py
turbocore/ai/__main__.py
turbocore/ai/openai/__init__.py
turbocore/ai/openai/__main__.py
turbocore/dc/__init__.py
turbocore/dc/__main__.py
turbocore/dev/__init__.py
turbocore/dev/__main__.py
turbocore/disk/__init__.py
turbocore/disk/enc/__init__.py
turbocore/disk/enc/__main__.py
turbocore/freeway/__init__.py
turbocore/freeway/__main__.py
turbocore/gen/__init__.py
turbocore/gen/py/__init__.py
turbocore/gen/py/flask/__init__.py
turbocore/gen/py/flask/__main__.py
turbocore/github/__init__.py
turbocore/github/__main__.py
turbocore/gpg/__init__.py
turbocore/gpg/__main__.py
turbocore/hz/__init__.py
turbocore/hz/__main__.py
turbocore/hz/dns/__init__.py
turbocore/iospool/__init__.py
turbocore/jira/__init__.py
turbocore/jira/__main__.py
turbocore/log/__init__.py
turbocore/log/assembler/__init__.py
turbocore/log/assembler/__main__.py
turbocore/misc/__init__.py
turbocore/misc/__main__.py
turbocore/misc/dockerparse/__init__.py
turbocore/misc/dockerparse/__main__.py
turbocore/misc/laze/__init__.py
turbocore/misc/laze/__main__.py
turbocore/misc/logging/__init__.py
turbocore/misc/logging/apache/__init__.py
turbocore/misc/logging/apache/__main__.py
turbocore/misc/logging/condense/__init__.py
turbocore/misc/logging/condense/__main__.py
turbocore/misc/porter/__init__.py
turbocore/misc/porter/__main__.py
turbocore/misc/porto/__init__.py
turbocore/misc/porto/__main__.py
turbocore/misc/reflector/__init__.py
turbocore/misc/reflector/__main__.py
turbocore/misc/siggi/__init__.py
turbocore/misc/siggi/__main__.py
turbocore/misc/sshcompile/__init__.py
turbocore/misc/sshcompile/__main__.py
turbocore/mutt/__init__.py
turbocore/nobolt/__init__.py
turbocore/nobolt/__main__.py
turbocore/npm/__init__.py
turbocore/npm/analytics/__init__.py
turbocore/npm/analytics/__main__.py
turbocore/r/__init__.py
turbocore/r/__main__.py
turbocore/s3/__init__.py
turbocore/s3/__main__.py
turbocore/safety/__init__.py
turbocore/ssh/__init__.py
turbocore-0.35.1.dist-info/licenses/LICENSE
turbocore-0.35.1.dist-info/METADATA
turbocore-0.35.1.dist-info/WHEEL
turbocore-0.35.1.dist-info/top_level.txt
turbocore-0.35.1.dist-info/RECORD
